bad.py
bad_project-0.0.1.dist-info/METADATA
bad_project-0.0.1.dist-info/WHEEL
bad_project-0.0.1.dist-info/top_level.txt
bad_project-0.0.1.dist-info/RECORD
